NetHyTech_STT/__init__.py
NetHyTech_STT_Smruti-0.1.dist-info/METADATA
NetHyTech_STT_Smruti-0.1.dist-info/WHEEL
NetHyTech_STT_Smruti-0.1.dist-info/top_level.txt
NetHyTech_STT_Smruti-0.1.dist-info/RECORD
