Metadata-Version: 2.1
Name: NetHyTech-STT-Smruti
Version: 0.1
Summary: This is a speech-to-text package created by Smruti Nayak
Author: Smruti Nayak
Author-email: nayaksmrutiranjan38@gmail.com
Requires-Dist: selenium
Requires-Dist: webdriver-manager
